asyncrcon/__init__.py
asyncrcon/exceptions.py
asyncrcon/packet.py
asyncrcon/rcon.py
asyncrcon-1.1.4.dist-info/LICENSE
asyncrcon-1.1.4.dist-info/METADATA
asyncrcon-1.1.4.dist-info/WHEEL
asyncrcon-1.1.4.dist-info/top_level.txt
asyncrcon-1.1.4.dist-info/RECORD
