Metadata-Version: 2.1
Name: asyncrcon
Version: 1.1.4
Summary: Client implementation of Minecrafts RCON protocol using asyncio
Home-page: https://github.com/zekrotja/asyncrcon
Author: zekro
Author-email: contact@zekro.de
License: UNKNOWN
Download-URL: https://github.com/zekrotja/asyncrcon/archive/master.tar.gz
Platform: UNKNOWN
Classifier: Programming Language :: Python :: 3.6
Classifier: Programming Language :: Python :: 3.7
Classifier: License :: OSI Approved :: Apache Software License
Classifier: Operating System :: OS Independent
Classifier: Topic :: Software Development :: Libraries
